[{"__type__":"cc.SpriteFrame","content":{"name":"qiezi","texture":"77PiHWbntIXrum3MeXJb8e","rect":[8,2,16,28],"offset":[0,0],"originalSize":[32,32],"capInsets":[0,0,0,0]}},{"__type__":"cc.SpriteFrame","content":{"name":"white","texture":"86blIktnZPt4Cdbvf3C6yO","rect":[0,0,375,667],"offset":[0,0],"originalSize":[375,667],"capInsets":[0,0,0,0]}},{"__type__":"cc.EffectAsset","_name":"builtin-2d-sprite","properties":{"texture":{"type":13,"value":null},"alphaThreshold":{"value":0.5}},"techniques":[{"passes":[{"cullMode":0,"blend":true,"program":"cea1abc1cddcfe17654f435ec4a977f72769819d4d7c0460b90eedb5"}],"layer":0,"stages":["opaque"],"queue":0,"priority":0}],"shaders":[{"vert":"\n#define _IS_VERT_SHADER 1\n\nprecision highp float;\n\nuniform mat4 cc_matViewProj;\n\n#if _USE_MODEL\n  uniform mat4 cc_matWorld;\n#endif\n\nattribute vec3 a_position;\nattribute lowp vec4 a_color;\n\n#if USE_TEXTURE\n  attribute mediump vec2 a_uv0;\n  varying mediump vec2 v_uv0;\n#endif\n\nvarying lowp vec4 v_color;\n\nvoid main () {\n  mat4 mvp;\n  \n  #if _USE_MODEL\n    mvp = cc_matViewProj * cc_matWorld;\n  #else\n    mvp = cc_matViewProj;\n  #endif\n\n  #if USE_TEXTURE\n    v_uv0 = a_uv0;\n  #endif\n\n  v_color = a_color;\n\n  gl_Position = mvp * vec4(a_position, 1);\n}\n\n\n","frag":"\n#define _IS_FRAG_SHADER 1\n\nprecision highp float;\n\n#if USE_TEXTURE\n  uniform sampler2D texture;\n  varying mediump vec2 v_uv0;\n#endif\n\n#if USE_ALPHA_TEST\n  uniform float alphaThreshold;\n#endif\n\nvoid ALPHA_TEST (in vec4 color) {\n  #if USE_ALPHA_TEST\n      if (color.a < alphaThreshold) discard;\n  #endif\n}\n\nvoid ALPHA_TEST (in float alpha) {\n  #if USE_ALPHA_TEST\n      if (alpha < alphaThreshold) discard;\n  #endif\n}\n\nvarying lowp vec4 v_color;\n\nvoid main () {\n  vec4 color = v_color;\n\n  #if USE_TEXTURE\n    color *= texture2D(texture, v_uv0);\n    #if _USE_ETC1_TEXTURE\n      color.a *= texture2D(texture, v_uv0 + vec2(0, 0.5)).r;\n    #endif\n  #endif\n\n  ALPHA_TEST(color);\n\n  gl_FragColor = color;\n}\n\n\n","defines":[{"name":"_USE_MODEL","type":"boolean","defines":[]},{"name":"USE_TEXTURE","type":"boolean","defines":[]},{"name":"USE_ALPHA_TEST","type":"boolean","defines":[]},{"name":"_USE_ETC1_TEXTURE","type":"boolean","defines":["USE_TEXTURE"]}],"uniforms":[{"name":"texture","type":13,"defines":["USE_TEXTURE"]},{"name":"alphaThreshold","type":4,"property":true,"defines":["USE_ALPHA_TEST"]}],"attributes":[{"name":"a_position","type":6,"defines":[]},{"name":"a_color","type":7,"defines":[]},{"name":"a_uv0","type":5,"defines":["USE_TEXTURE"]}],"extensions":[],"name":"cea1abc1cddcfe17654f435ec4a977f72769819d4d7c0460b90eedb5"}]},{"__type__":"cc.SpriteFrame","content":{"name":"close","texture":"81Gm1KlVhAmr/ym3RZhzk0","rect":[6,6,52,52],"offset":[0,0],"originalSize":[64,64],"capInsets":[0,0,0,0]}},[{"__type__":"cc.SceneAsset","_name":"game","scene":{"__id__":1},"asyncLoadAssets":null},{"__type__":"cc.Scene","_name":"New Node","_children":[{"__id__":2}],"_active":false,"_anchorPoint":{"__type__":"cc.Vec2"},"autoReleaseAssets":false},{"__type__":"cc.Node","_name":"Canvas","_parent":{"__id__":1},"_children":[{"__id__":3},{"__id__":4},{"__id__":6},{"__id__":8},{"__id__":9},{"__id__":14},{"__id__":15},{"__id__":20}],"_level":1,"_components":[{"__type__":"cc.Canvas","node":{"__id__":2},"_designResolution":{"__type__":"cc.Size","width":375,"height":667},"_fitWidth":true,"_fitHeight":false},{"__type__":"65f57bZhO1ESZsGHmmKX+OK","node":{"__id__":2},"ranking":{"__uuid__":"9cY9vE8WBJx6JbDxvqkjR9"}},{"__type__":"cc.Sprite","node":{"__id__":2},"_materials":[{"__uuid__":"ecpdLyjvZBwrvm+cedCcQy"}],"_spriteFrame":{"__uuid__":"11bXQ00HZLupZHntrPqaSp"}},{"__type__":"cc.Widget","node":{"__id__":2},"_alignFlags":45,"_originalWidth":375,"_originalHeight":667}],"_color":{"__type__":"cc.Color","r":80,"g":92,"b":179},"_contentSize":{"__type__":"cc.Size","width":375,"height":667},"_position":{"__type__":"cc.Vec3","x":187.5,"y":333.5},"_id":"e821HNPRBCkqaT1fMk9fFR"},{"__type__":"cc.Node","_name":"Main Camera","_parent":{"__id__":2},"_level":2,"_components":[{"__type__":"cc.Camera","node":{"__id__":3},"_clearFlags":7,"_depth":-1}],"_position":{"__type__":"cc.Vec3","z":458.1274386019681}},{"__type__":"cc.Node","_name":"group1","_parent":{"__id__":2},"_children":[{"__id__":5}],"_level":2,"_components":[{"__type__":"cc.Widget","node":{"__id__":4},"_alignFlags":45,"_right":190,"_originalWidth":185,"_originalHeight":667},{"__type__":"c8b88ku6A9MKLMYPBj3vbiN","node":{"__id__":4},"branchpreL":{"__uuid__":"df9WKLkbtKKamVlAxvPBGc"},"branchpreR":{"__uuid__":"aeKlXK1phE/pC9M6FahaVo"}},{"__type__":"cc.Sprite","node":{"__id__":4},"_materials":[{"__uuid__":"ecpdLyjvZBwrvm+cedCcQy"}],"_spriteFrame":{"__uuid__":"11bXQ00HZLupZHntrPqaSp"},"_sizeMode":0}],"_color":{"__type__":"cc.Color","r":197,"g":202,"b":63},"_contentSize":{"__type__":"cc.Size","width":185,"height":667},"_anchorPoint":{"__type__":"cc.Vec2"},"_position":{"__type__":"cc.Vec3","x":-187.5,"y":-333.5}},{"__type__":"cc.Node","_name":"lead","_parent":{"__id__":4},"_level":3,"_components":[{"__type__":"cc.Sprite","node":{"__id__":5},"_materials":[{"__uuid__":"ecpdLyjvZBwrvm+cedCcQy"}],"_spriteFrame":{"__uuid__":"10kc7U2MBMlZb/XX7THScP"}},{"__type__":"cc.Widget","node":{"__id__":5},"_alignFlags":10,"_bottom":100},{"__type__":"3e20do9TxFPjrEMXWK/sW/2","node":{"__id__":5}},{"__type__":"cc.PolygonCollider","node":{"__id__":5},"points":[{"__type__":"cc.Vec2","x":6,"y":28},{"__type__":"cc.Vec2","x":6,"y":26},{"__type__":"cc.Vec2","x":3,"y":25},{"__type__":"cc.Vec2","x":4,"y":19},{"__type__":"cc.Vec2","y":10},{"__type__":"cc.Vec2","y":4},{"__type__":"cc.Vec2","x":3},{"__type__":"cc.Vec2","x":13},{"__type__":"cc.Vec2","x":16,"y":4},{"__type__":"cc.Vec2","x":16,"y":10},{"__type__":"cc.Vec2","x":13,"y":16},{"__type__":"cc.Vec2","x":13,"y":25},{"__type__":"cc.Vec2","x":10,"y":26},{"__type__":"cc.Vec2","x":10,"y":28}]}],"_contentSize":{"__type__":"cc.Size","width":16,"height":28},"_anchorPoint":{"__type__":"cc.Vec2"},"_position":{"__type__":"cc.Vec3","y":319.5},"groupIndex":1},{"__type__":"cc.Node","_name":"group2","_parent":{"__id__":2},"_children":[{"__id__":7}],"_level":2,"_components":[{"__type__":"cc.Widget","node":{"__id__":6},"_alignFlags":45,"_left":190,"_originalWidth":185,"_originalHeight":667},{"__type__":"5df48gaA05NIoo/J4tNrUuV","node":{"__id__":6},"branchpreL":{"__uuid__":"df9WKLkbtKKamVlAxvPBGc"},"branchpreR":{"__uuid__":"aeKlXK1phE/pC9M6FahaVo"}},{"__type__":"cc.Sprite","node":{"__id__":6},"_materials":[{"__uuid__":"ecpdLyjvZBwrvm+cedCcQy"}],"_spriteFrame":{"__uuid__":"11bXQ00HZLupZHntrPqaSp"},"_sizeMode":0}],"_color":{"__type__":"cc.Color","r":195,"g":97,"b":97},"_contentSize":{"__type__":"cc.Size","width":185,"height":667},"_anchorPoint":{"__type__":"cc.Vec2"},"_position":{"__type__":"cc.Vec3","x":2.5,"y":-333.5}},{"__type__":"cc.Node","_name":"lead","_parent":{"__id__":6},"_level":3,"_components":[{"__type__":"cc.Sprite","node":{"__id__":7},"_materials":[{"__uuid__":"ecpdLyjvZBwrvm+cedCcQy"}],"_spriteFrame":{"__uuid__":"10kc7U2MBMlZb/XX7THScP"}},{"__type__":"cc.Widget","node":{"__id__":7},"_alignFlags":10,"_bottom":100},{"__type__":"3e20do9TxFPjrEMXWK/sW/2","node":{"__id__":7}},{"__type__":"cc.PolygonCollider","node":{"__id__":7},"points":[{"__type__":"cc.Vec2","x":6,"y":28},{"__type__":"cc.Vec2","x":6,"y":26},{"__type__":"cc.Vec2","x":3,"y":25},{"__type__":"cc.Vec2","x":4,"y":19},{"__type__":"cc.Vec2","y":10},{"__type__":"cc.Vec2","y":4},{"__type__":"cc.Vec2","x":3},{"__type__":"cc.Vec2","x":13},{"__type__":"cc.Vec2","x":16,"y":4},{"__type__":"cc.Vec2","x":16,"y":10},{"__type__":"cc.Vec2","x":13,"y":16},{"__type__":"cc.Vec2","x":13,"y":25},{"__type__":"cc.Vec2","x":10,"y":26},{"__type__":"cc.Vec2","x":10,"y":28}]}],"_contentSize":{"__type__":"cc.Size","width":16,"height":28},"_anchorPoint":{"__type__":"cc.Vec2"},"_position":{"__type__":"cc.Vec3","y":319.5},"groupIndex":1},{"__type__":"cc.Node","_name":"score","_parent":{"__id__":2},"_level":2,"_components":[{"__type__":"cc.Label","node":{"__id__":8},"_materials":[{"__uuid__":"ecpdLyjvZBwrvm+cedCcQy"}],"_useOriginalSize":false,"_string":"score:0","_N$string":"score:0","_N$horizontalAlign":1,"_N$verticalAlign":1},{"__type__":"cc.Widget","node":{"__id__":8},"_alignFlags":17,"_top":16.5}],"_contentSize":{"__type__":"cc.Size","width":131.17,"height":50.4},"_position":{"__type__":"cc.Vec3","y":291.8}},{"__type__":"cc.Node","_name":"index","_parent":{"__id__":2},"_children":[{"__id__":10},{"__id__":11},{"__id__":12},{"__id__":13}],"_level":2,"_components":[{"__type__":"cc.Sprite","node":{"__id__":9},"_materials":[{"__uuid__":"ecpdLyjvZBwrvm+cedCcQy"}],"_spriteFrame":{"__uuid__":"11bXQ00HZLupZHntrPqaSp"}},{"__type__":"cc.Widget","node":{"__id__":9},"_alignFlags":45,"_originalWidth":375,"_originalHeight":667}],"_color":{"__type__":"cc.Color","r":89,"g":182,"b":96},"_contentSize":{"__type__":"cc.Size","width":375,"height":667}},{"__type__":"cc.Node","_name":"name","_parent":{"__id__":9},"_level":3,"_components":[{"__type__":"cc.Label","node":{"__id__":10},"_materials":[{"__uuid__":"ecpdLyjvZBwrvm+cedCcQy"}],"_useOriginalSize":false,"_string":"比翼双飞","_N$string":"比翼双飞","_N$horizontalAlign":1,"_N$verticalAlign":1},{"__type__":"cc.Widget","node":{"__id__":10},"_alignFlags":17,"_top":96.5}],"_contentSize":{"__type__":"cc.Size","width":160,"height":50.4},"_position":{"__type__":"cc.Vec3","y":211.8}},{"__type__":"cc.Node","_name":"score","_parent":{"__id__":9},"_level":3,"_components":[{"__type__":"cc.Label","node":{"__id__":11},"_materials":[{"__uuid__":"ecpdLyjvZBwrvm+cedCcQy"}],"_useOriginalSize":false,"_string":"得分:0","_N$string":"得分:0","_N$horizontalAlign":1,"_N$verticalAlign":1},{"__type__":"cc.Widget","node":{"__id__":11},"_alignFlags":18,"_top":290.5,"_verticalCenter":61}],"_contentSize":{"__type__":"cc.Size","width":113.36,"height":50.4},"_position":{"__type__":"cc.Vec3","y":61}},{"__type__":"cc.Node","_name":"play","_parent":{"__id__":9},"_level":3,"_components":[{"__type__":"cc.Label","node":{"__id__":12},"_materials":[{"__uuid__":"ecpdLyjvZBwrvm+cedCcQy"}],"_useOriginalSize":false,"_string":"play","_N$string":"play","_N$horizontalAlign":1,"_N$verticalAlign":1},{"__type__":"cc.Widget","node":{"__id__":12},"_alignFlags":20,"_top":451.5,"_bottom":236.5,"_originalHeight":40},{"__type__":"cc.Button","node":{"__id__":12},"clickEvents":[{"__type__":"cc.ClickEvent","target":{"__id__":2},"_componentId":"65f57bZhO1ESZsGHmmKX+OK","handler":"gameStart"}],"_N$normalColor":{"__type__":"cc.Color","r":214,"g":214,"b":214}}],"_contentSize":{"__type__":"cc.Size","width":73.38,"height":50.4},"_position":{"__type__":"cc.Vec3","y":-71.8}},{"__type__":"cc.Node","_name":"rank","_parent":{"__id__":9},"_level":3,"_components":[{"__type__":"cc.Label","node":{"__id__":13},"_materials":[{"__uuid__":"ecpdLyjvZBwrvm+cedCcQy"}],"_useOriginalSize":false,"_string":"排行榜","_N$string":"排行榜","_N$horizontalAlign":1,"_N$verticalAlign":1},{"__type__":"cc.Button","node":{"__id__":13},"clickEvents":[{"__type__":"cc.ClickEvent","target":{"__id__":2},"_componentId":"65f57bZhO1ESZsGHmmKX+OK","handler":"openRank"}],"_N$normalColor":{"__type__":"cc.Color","r":214,"g":214,"b":214}}],"_contentSize":{"__type__":"cc.Size","width":120,"height":50.4},"_position":{"__type__":"cc.Vec3","y":-225}},{"__type__":"cc.Node","_name":"WebView","_parent":{"__id__":2},"_active":false,"_level":2,"_components":[{"__type__":"cc.WebView","node":{"__id__":14},"_useOriginalSize":false,"_url":"https://dev.imapi.zhenmanapp.com/static/html/ivcode.html?code=#/"},{"__type__":"cc.Widget","node":{"__id__":14},"_alignFlags":45,"_originalWidth":300,"_originalHeight":200}],"_contentSize":{"__type__":"cc.Size","width":375,"height":667}},{"__type__":"cc.Node","_name":"countDown","_parent":{"__id__":2},"_children":[{"__id__":16},{"__id__":17},{"__id__":18},{"__id__":19}],"_active":false,"_level":2,"_components":[{"__type__":"cc.Sprite","node":{"__id__":15},"_spriteFrame":{"__uuid__":"11bXQ00HZLupZHntrPqaSp"},"_sizeMode":0}],"_contentSize":{"__type__":"cc.Size","width":300,"height":250}},{"__type__":"cc.Node","_name":"hint","_parent":{"__id__":15},"_level":3,"_components":[{"__type__":"cc.Label","node":{"__id__":16},"_useOriginalSize":false,"_string":"是否消耗三个茄子续命？","_N$string":"是否消耗三个茄子续命？","_N$horizontalAlign":1,"_N$verticalAlign":1,"_N$overflow":2},{"__type__":"cc.Widget","node":{"__id__":16},"_alignFlags":40,"_left":10,"_right":10,"_originalWidth":440}],"_color":{"__type__":"cc.Color"},"_contentSize":{"__type__":"cc.Size","width":280,"height":40},"_position":{"__type__":"cc.Vec3","y":75}},{"__type__":"cc.Node","_name":"time","_parent":{"__id__":15},"_level":3,"_components":[{"__type__":"cc.Label","node":{"__id__":17},"_useOriginalSize":false,"_string":"5","_N$string":"5","_N$horizontalAlign":1,"_N$verticalAlign":1}],"_color":{"__type__":"cc.Color"},"_contentSize":{"__type__":"cc.Size","width":22.25,"height":40}},{"__type__":"cc.Node","_name":"yes","_parent":{"__id__":15},"_level":3,"_components":[{"__type__":"cc.Label","node":{"__id__":18},"_useOriginalSize":false,"_string":"yes","_N$string":"yes","_N$horizontalAlign":1,"_N$verticalAlign":1},{"__type__":"cc.Widget","node":{"__id__":18},"_alignFlags":12,"_left":20,"_bottom":30},{"__type__":"cc.Button","node":{"__id__":18},"clickEvents":[{"__type__":"cc.ClickEvent","target":{"__id__":2},"_componentId":"65f57bZhO1ESZsGHmmKX+OK","handler":"keepOn"}],"_N$normalColor":{"__type__":"cc.Color","r":214,"g":214,"b":214}}],"_color":{"__type__":"cc.Color","r":255,"g":29,"b":29},"_contentSize":{"__type__":"cc.Size","width":62.25,"height":40},"_position":{"__type__":"cc.Vec3","x":-98.875,"y":-75}},{"__type__":"cc.Node","_name":"no","_parent":{"__id__":15},"_level":3,"_components":[{"__type__":"cc.Label","node":{"__id__":19},"_useOriginalSize":false,"_string":"no","_N$string":"no","_N$horizontalAlign":1,"_N$verticalAlign":1},{"__type__":"cc.Widget","node":{"__id__":19},"_alignFlags":36,"_left":28.88,"_right":20,"_bottom":30},{"__type__":"cc.Button","node":{"__id__":19},"clickEvents":[{"__type__":"cc.ClickEvent","target":{"__id__":2},"_componentId":"65f57bZhO1ESZsGHmmKX+OK","handler":"gameover"}],"_N$normalColor":{"__type__":"cc.Color","r":214,"g":214,"b":214}}],"_color":{"__type__":"cc.Color"},"_contentSize":{"__type__":"cc.Size","width":44.49,"height":40},"_position":{"__type__":"cc.Vec3","x":107.755,"y":-75}},{"__type__":"cc.Node","_name":"pop","_parent":{"__id__":2},"_children":[{"__id__":21},{"__id__":22},{"__id__":23}],"_active":false,"_level":2,"_components":[{"__type__":"cc.Sprite","node":{"__id__":20},"_spriteFrame":{"__uuid__":"11bXQ00HZLupZHntrPqaSp"},"_sizeMode":0}],"_contentSize":{"__type__":"cc.Size","width":300,"height":250}},{"__type__":"cc.Node","_name":"hint","_parent":{"__id__":20},"_level":3,"_components":[{"__type__":"cc.Label","node":{"__id__":21},"_useOriginalSize":false,"_string":"分享好友可以获得茄子，是否分享","_N$string":"分享好友可以获得茄子，是否分享","_N$horizontalAlign":1,"_N$verticalAlign":1,"_N$overflow":2},{"__type__":"cc.Widget","node":{"__id__":21},"_alignFlags":40,"_left":10,"_right":10,"_originalWidth":440}],"_color":{"__type__":"cc.Color"},"_contentSize":{"__type__":"cc.Size","width":280,"height":80},"_position":{"__type__":"cc.Vec3","y":42}},{"__type__":"cc.Node","_name":"no","_parent":{"__id__":20},"_level":3,"_components":[{"__type__":"cc.Label","node":{"__id__":22},"_useOriginalSize":false,"_string":"no","_N$string":"no","_N$horizontalAlign":1,"_N$verticalAlign":1},{"__type__":"cc.Widget","node":{"__id__":22},"_alignFlags":36,"_left":28.88,"_right":30,"_bottom":33},{"__type__":"cc.Button","node":{"__id__":22},"clickEvents":[{"__type__":"cc.ClickEvent","target":{"__id__":2},"_componentId":"65f57bZhO1ESZsGHmmKX+OK","handler":"gameover"}],"_N$normalColor":{"__type__":"cc.Color","r":214,"g":214,"b":214}}],"_color":{"__type__":"cc.Color"},"_contentSize":{"__type__":"cc.Size","width":44.49,"height":40},"_position":{"__type__":"cc.Vec3","x":97.755,"y":-72}},{"__type__":"cc.Node","_name":"yes","_parent":{"__id__":20},"_level":3,"_components":[{"__type__":"cc.Label","node":{"__id__":23},"_useOriginalSize":false,"_string":"yes","_N$string":"yes","_N$horizontalAlign":1,"_N$verticalAlign":1},{"__type__":"cc.Widget","node":{"__id__":23},"_alignFlags":12,"_left":30,"_bottom":33},{"__type__":"cc.Button","node":{"__id__":23},"clickEvents":[{"__type__":"cc.ClickEvent","target":{"__id__":2},"_componentId":"65f57bZhO1ESZsGHmmKX+OK","handler":"showShareAlert"}],"_N$normalColor":{"__type__":"cc.Color","r":214,"g":214,"b":214}}],"_color":{"__type__":"cc.Color"},"_contentSize":{"__type__":"cc.Size","width":62.25,"height":40},"_position":{"__type__":"cc.Vec3","x":-88.875,"y":-72}}],{"__type__":"cc.Texture2D","content":"0,9729,9729,33071,33071,0,0,1"},{"__type__":"cc.Texture2D","content":"0,9729,9729,33071,33071,0,0,1"},{"__type__":"cc.Texture2D","content":"0,9729,9729,33071,33071,0,0,1"},[{"__type__":"cc.Prefab","_name":"rankinglist","data":{"__id__":1}},{"__type__":"cc.Node","_name":"rankinglist","_children":[{"__id__":2},{"__id__":3},{"__id__":7},{"__id__":11},{"__id__":14}],"_active":false,"_level":1,"_components":[{"__type__":"cc.Sprite","node":{"__id__":1},"_spriteFrame":{"__uuid__":"11bXQ00HZLupZHntrPqaSp"},"_sizeMode":0},{"__type__":"cc.Widget","node":{"__id__":1},"_alignFlags":45,"_originalWidth":375,"_originalHeight":667},{"__type__":"22d75u8i1xFrJHU3UzxXEub","node":{"__id__":1},"title":{"__id__":3},"content":{"__id__":13},"rowPre":{"__uuid__":"fb75PannNN0YjFKlqXw8gS"}}],"_prefab":{"__type__":"cc.PrefabInfo","root":{"__id__":1},"asset":{"__uuid__":"9cY9vE8WBJx6JbDxvqkjR9"},"fileId":"33b3h00ZlMg64/OQoIhrvq"},"_color":{"__type__":"cc.Color","r":10,"g":10,"b":10},"_contentSize":{"__type__":"cc.Size","width":375,"height":667},"_position":{"__type__":"cc.Vec3","x":187.5,"y":333.5}},{"__type__":"cc.Node","_name":"close","_parent":{"__id__":1},"_level":3,"_components":[{"__type__":"cc.Sprite","node":{"__id__":2},"_spriteFrame":{"__uuid__":"42ZBUWvTZPRIMKMzt7N+XW"},"_sizeMode":0},{"__type__":"cc.Widget","node":{"__id__":2},"_alignFlags":33,"_right":10,"_top":10},{"__type__":"cc.Button","node":{"__id__":2},"clickEvents":[{"__type__":"cc.ClickEvent","target":{"__id__":1},"_componentId":"22d75u8i1xFrJHU3UzxXEub","handler":"closeNode"}],"_N$normalColor":{"__type__":"cc.Color","r":214,"g":214,"b":214}}],"_prefab":{"__type__":"cc.PrefabInfo","root":{"__id__":1},"asset":{"__uuid__":"9cY9vE8WBJx6JbDxvqkjR9"},"fileId":"a0YrY+BmZI/5Mi8z69h764"},"_color":{"__type__":"cc.Color","r":231,"g":245,"b":233},"_contentSize":{"__type__":"cc.Size","width":30,"height":30},"_position":{"__type__":"cc.Vec3","x":162.5,"y":308.5}},{"__type__":"cc.Node","_name":"title","_parent":{"__id__":1},"_children":[{"__id__":4},{"__id__":5},{"__id__":6}],"_level":3,"_components":[{"__type__":"cc.Sprite","node":{"__id__":3},"_sizeMode":0},{"__type__":"cc.Widget","node":{"__id__":3},"_alignFlags":41,"_left":10,"_right":10,"_top":42.5,"_bottom":574.5,"_originalWidth":375,"_originalHeight":50},{"__type__":"cc.Layout","node":{"__id__":3},"_layoutSize":{"__type__":"cc.Size","width":355,"height":50},"_resize":1,"_N$layoutType":1,"_N$paddingLeft":10,"_N$paddingRight":10,"_N$spacingX":20}],"_prefab":{"__type__":"cc.PrefabInfo","root":{"__id__":1},"asset":{"__uuid__":"9cY9vE8WBJx6JbDxvqkjR9"},"fileId":"fdYaF0Z+dMmrNw9tMB5BWN"},"_color":{"__type__":"cc.Color","r":240,"g":238,"b":225},"_contentSize":{"__type__":"cc.Size","width":355,"height":50},"_position":{"__type__":"cc.Vec3","y":266}},{"__type__":"cc.Node","_name":"friend","_parent":{"__id__":3},"_level":4,"_components":[{"__type__":"cc.Label","node":{"__id__":4},"_useOriginalSize":false,"_string":"friend","_N$string":"friend","_N$horizontalAlign":1,"_N$verticalAlign":1,"_N$overflow":2},{"__type__":"cc.Button","node":{"__id__":4},"clickEvents":[{"__type__":"cc.ClickEvent","target":{"__id__":1},"_componentId":"22d75u8i1xFrJHU3UzxXEub","handler":"updateList","customEventData":"friend"}],"_N$normalColor":{"__type__":"cc.Color","r":214,"g":214,"b":214}}],"_prefab":{"__type__":"cc.PrefabInfo","root":{"__id__":1},"asset":{"__uuid__":"9cY9vE8WBJx6JbDxvqkjR9"},"fileId":"48IqDLIqhKRpX2AZZ+9Dz2"},"_opacity":219,"_color":{"__type__":"cc.Color","r":255},"_contentSize":{"__type__":"cc.Size","width":98.33333333333333,"height":40},"_position":{"__type__":"cc.Vec3","x":-118.33333333333334}},{"__type__":"cc.Node","_name":"team","_parent":{"__id__":3},"_level":4,"_components":[{"__type__":"cc.Label","node":{"__id__":5},"_useOriginalSize":false,"_string":"team","_N$string":"team","_N$horizontalAlign":1,"_N$verticalAlign":1,"_N$overflow":2},{"__type__":"cc.Button","node":{"__id__":5},"clickEvents":[{"__type__":"cc.ClickEvent","target":{"__id__":1},"_componentId":"22d75u8i1xFrJHU3UzxXEub","handler":"updateList","customEventData":"team"}],"_N$normalColor":{"__type__":"cc.Color","r":214,"g":214,"b":214}}],"_prefab":{"__type__":"cc.PrefabInfo","root":{"__id__":1},"asset":{"__uuid__":"9cY9vE8WBJx6JbDxvqkjR9"},"fileId":"86XmVnUxZIzoYxV7N7mK/i"},"_contentSize":{"__type__":"cc.Size","width":98.33333333333333,"height":40},"_position":{"__type__":"cc.Vec3","x":-2.1316282072803006e-14}},{"__type__":"cc.Node","_name":"world","_parent":{"__id__":3},"_level":4,"_components":[{"__type__":"cc.Label","node":{"__id__":6},"_useOriginalSize":false,"_string":"world","_N$string":"world","_N$horizontalAlign":1,"_N$verticalAlign":1,"_N$overflow":2},{"__type__":"cc.Button","node":{"__id__":6},"clickEvents":[{"__type__":"cc.ClickEvent","target":{"__id__":1},"_componentId":"22d75u8i1xFrJHU3UzxXEub","handler":"updateList","customEventData":"world"}],"_N$normalColor":{"__type__":"cc.Color","r":214,"g":214,"b":214}}],"_prefab":{"__type__":"cc.PrefabInfo","root":{"__id__":1},"asset":{"__uuid__":"9cY9vE8WBJx6JbDxvqkjR9"},"fileId":"c4DYwo0pZH0Jgi0iR0b7xW"},"_contentSize":{"__type__":"cc.Size","width":98.33333333333333,"height":40},"_position":{"__type__":"cc.Vec3","x":118.33333333333331}},{"__type__":"cc.Node","_name":"listTitle","_parent":{"__id__":1},"_children":[{"__id__":8},{"__id__":9},{"__id__":10}],"_level":3,"_components":[{"__type__":"cc.Sprite","node":{"__id__":7},"_sizeMode":0},{"__type__":"cc.Widget","node":{"__id__":7},"_alignFlags":41,"_left":10,"_right":10,"_top":88.5,"_bottom":528.5,"_originalWidth":375,"_originalHeight":50},{"__type__":"cc.Layout","node":{"__id__":7},"_resize":2,"_N$layoutType":1,"_N$paddingLeft":10,"_N$paddingRight":10,"_N$spacingX":20}],"_prefab":{"__type__":"cc.PrefabInfo","root":{"__id__":1},"asset":{"__uuid__":"9cY9vE8WBJx6JbDxvqkjR9"},"fileId":"07Nznuu8VK/Kan5XHDVbgt"},"_color":{"__type__":"cc.Color","r":67,"g":202,"b":94},"_contentSize":{"__type__":"cc.Size","width":355,"height":50},"_position":{"__type__":"cc.Vec3","y":220}},{"__type__":"cc.Node","_name":"rank","_parent":{"__id__":7},"_level":4,"_components":[{"__type__":"cc.Label","node":{"__id__":8},"_useOriginalSize":false,"_string":"rank","_N$string":"rank","_N$horizontalAlign":1,"_N$verticalAlign":1,"_N$overflow":2}],"_prefab":{"__type__":"cc.PrefabInfo","root":{"__id__":1},"asset":{"__uuid__":"9cY9vE8WBJx6JbDxvqkjR9"},"fileId":"c96NlXpJNL+5qHTBpjFaI3"},"_contentSize":{"__type__":"cc.Size","width":98.33333333333333,"height":40},"_position":{"__type__":"cc.Vec3","x":-118.33333333333334}},{"__type__":"cc.Node","_name":"name","_parent":{"__id__":7},"_level":4,"_components":[{"__type__":"cc.Label","node":{"__id__":9},"_useOriginalSize":false,"_string":"name","_N$string":"name","_N$horizontalAlign":1,"_N$verticalAlign":1,"_N$overflow":2}],"_prefab":{"__type__":"cc.PrefabInfo","root":{"__id__":1},"asset":{"__uuid__":"9cY9vE8WBJx6JbDxvqkjR9"},"fileId":"22dqrnsEhAaLvgbAdZ8Snm"},"_contentSize":{"__type__":"cc.Size","width":98.33333333333333,"height":40},"_position":{"__type__":"cc.Vec3","x":-2.1316282072803006e-14}},{"__type__":"cc.Node","_name":"score","_parent":{"__id__":7},"_level":4,"_components":[{"__type__":"cc.Label","node":{"__id__":10},"_useOriginalSize":false,"_string":"score","_N$string":"score","_N$horizontalAlign":1,"_N$verticalAlign":1,"_N$overflow":2}],"_prefab":{"__type__":"cc.PrefabInfo","root":{"__id__":1},"asset":{"__uuid__":"9cY9vE8WBJx6JbDxvqkjR9"},"fileId":"63ODSveV5Jtblzmas1HgYU"},"_contentSize":{"__type__":"cc.Size","width":98.33333333333333,"height":40},"_position":{"__type__":"cc.Vec3","x":118.33333333333331}},{"__type__":"cc.Node","_name":"list","_parent":{"__id__":1},"_children":[{"__id__":12}],"_level":3,"_components":[{"__type__":"cc.Sprite","node":{"__id__":11},"_sizeMode":0},{"__type__":"cc.Widget","node":{"__id__":11},"_target":{"__id__":1},"_alignFlags":45,"_top":159,"_bottom":121,"_originalWidth":375,"_originalHeight":387},{"__type__":"cc.ScrollView","node":{"__id__":11},"horizontal":false,"brake":0.75,"bounceDuration":0.23,"scrollEvents":[{"__type__":"cc.ClickEvent","target":{"__id__":1},"_componentId":"22d75u8i1xFrJHU3UzxXEub","handler":"getCharts"}],"_N$content":{"__id__":13},"content":{"__id__":13}}],"_prefab":{"__type__":"cc.PrefabInfo","root":{"__id__":1},"asset":{"__uuid__":"9cY9vE8WBJx6JbDxvqkjR9"},"fileId":"42DfUZVftJvJENM2zuppFF"},"_contentSize":{"__type__":"cc.Size","width":375,"height":387},"_position":{"__type__":"cc.Vec3","y":-19}},{"__type__":"cc.Node","_name":"mask","_parent":{"__id__":11},"_children":[{"__id__":13}],"_level":4,"_components":[{"__type__":"cc.Mask","node":{"__id__":12}},{"__type__":"cc.Widget","node":{"__id__":12},"_alignFlags":45}],"_prefab":{"__type__":"cc.PrefabInfo","root":{"__id__":1},"asset":{"__uuid__":"9cY9vE8WBJx6JbDxvqkjR9"},"fileId":"872Fo2u7tMDoO951CGtB0v"},"_contentSize":{"__type__":"cc.Size","width":375,"height":387}},{"__type__":"cc.Node","_name":"content","_parent":{"__id__":12},"_level":5,"_components":[{"__type__":"cc.Widget","node":{"__id__":13},"_target":{"__id__":11},"_alignFlags":40,"_top":100,"_bottom":227,"_originalHeight":80},{"__type__":"cc.Layout","node":{"__id__":13},"_layoutSize":{"__type__":"cc.Size","width":375,"height":80},"_resize":1,"_N$layoutType":2}],"_prefab":{"__type__":"cc.PrefabInfo","root":{"__id__":1},"asset":{"__uuid__":"9cY9vE8WBJx6JbDxvqkjR9"},"fileId":"479YoB6tVD75VLwn26ycJl"},"_contentSize":{"__type__":"cc.Size","width":375,"height":80},"_position":{"__type__":"cc.Vec3","y":53.5}},{"__type__":"cc.Node","_name":"my","_parent":{"__id__":1},"_children":[{"__id__":15},{"__id__":16},{"__id__":17}],"_level":3,"_components":[{"__type__":"cc.Sprite","node":{"__id__":14},"_sizeMode":0},{"__type__":"cc.Widget","node":{"__id__":14},"_alignFlags":44,"_left":10,"_right":10,"_top":548.5,"_bottom":38.5,"_originalWidth":375,"_originalHeight":80},{"__type__":"cc.Layout","node":{"__id__":14},"_layoutSize":{"__type__":"cc.Size","width":355,"height":80},"_resize":2,"_N$layoutType":1,"_N$paddingLeft":10,"_N$paddingRight":10,"_N$spacingX":20}],"_prefab":{"__type__":"cc.PrefabInfo","root":{"__id__":1},"asset":{"__uuid__":"9cY9vE8WBJx6JbDxvqkjR9"},"fileId":"9fDR/JCgFHSbWSyzU5d1PE"},"_color":{"__type__":"cc.Color","r":67,"g":202,"b":94},"_contentSize":{"__type__":"cc.Size","width":355,"height":80},"_position":{"__type__":"cc.Vec3","y":-255}},{"__type__":"cc.Node","_name":"rank","_parent":{"__id__":14},"_level":4,"_components":[{"__type__":"cc.Label","node":{"__id__":15},"_useOriginalSize":false,"_string":"0","_N$string":"0","_N$horizontalAlign":1,"_N$verticalAlign":1,"_N$overflow":2}],"_prefab":{"__type__":"cc.PrefabInfo","root":{"__id__":1},"asset":{"__uuid__":"9cY9vE8WBJx6JbDxvqkjR9"},"fileId":"74R2mjJbhGwrouwwLfBKGn"},"_contentSize":{"__type__":"cc.Size","width":98.33333333333333,"height":40},"_position":{"__type__":"cc.Vec3","x":-118.33333333333334}},{"__type__":"cc.Node","_name":"name","_parent":{"__id__":14},"_level":4,"_components":[{"__type__":"cc.Label","node":{"__id__":16},"_useOriginalSize":false,"_string":"shuai","_N$string":"shuai","_N$horizontalAlign":1,"_N$verticalAlign":1,"_N$overflow":2}],"_prefab":{"__type__":"cc.PrefabInfo","root":{"__id__":1},"asset":{"__uuid__":"9cY9vE8WBJx6JbDxvqkjR9"},"fileId":"d31wSbtapBD7fzW8WVtKZ/"},"_contentSize":{"__type__":"cc.Size","width":98.33333333333333,"height":40},"_position":{"__type__":"cc.Vec3","x":-2.1316282072803006e-14}},{"__type__":"cc.Node","_name":"score","_parent":{"__id__":14},"_level":4,"_components":[{"__type__":"cc.Label","node":{"__id__":17},"_useOriginalSize":false,"_string":"0","_N$string":"0","_N$horizontalAlign":1,"_N$verticalAlign":1,"_N$overflow":2}],"_prefab":{"__type__":"cc.PrefabInfo","root":{"__id__":1},"asset":{"__uuid__":"9cY9vE8WBJx6JbDxvqkjR9"},"fileId":"c6lbV81LdFcoWZVDyWn7v4"},"_contentSize":{"__type__":"cc.Size","width":98.33333333333333,"height":40},"_position":{"__type__":"cc.Vec3","x":118.33333333333331}}],[{"__type__":"cc.Prefab","_name":"branchRight","data":{"__id__":1}},{"__type__":"cc.Node","_name":"branchRight","_level":1,"_components":[{"__type__":"cc.Sprite","node":{"__id__":1},"_spriteFrame":{"__uuid__":"11bXQ00HZLupZHntrPqaSp"},"_sizeMode":0},{"__type__":"64105DfwEZEbJLpmYqDWmzD","node":{"__id__":1}},{"__type__":"cc.BoxCollider","node":{"__id__":1},"_size":{"__type__":"cc.Size","width":300,"height":30}}],"_prefab":{"__type__":"cc.PrefabInfo","root":{"__id__":1},"asset":{"__uuid__":"aeKlXK1phE/pC9M6FahaVo"},"fileId":"20M2EohFNPU5YsIHEtCAQp"},"_color":{"__type__":"cc.Color","r":72,"g":185,"b":94},"_contentSize":{"__type__":"cc.Size","width":300,"height":30},"_anchorPoint":{"__type__":"cc.Vec2","x":1},"_position":{"__type__":"cc.Vec3","x":473,"y":377},"groupIndex":2}],[{"__type__":"cc.Prefab","_name":"branchLeft","data":{"__id__":1}},{"__type__":"cc.Node","_name":"branchLeft","_level":1,"_components":[{"__type__":"cc.Sprite","node":{"__id__":1},"_spriteFrame":{"__uuid__":"11bXQ00HZLupZHntrPqaSp"},"_sizeMode":0},{"__type__":"64105DfwEZEbJLpmYqDWmzD","node":{"__id__":1}},{"__type__":"cc.BoxCollider","node":{"__id__":1},"_size":{"__type__":"cc.Size","width":300,"height":30}}],"_prefab":{"__type__":"cc.PrefabInfo","root":{"__id__":1},"asset":{"__uuid__":"df9WKLkbtKKamVlAxvPBGc"},"fileId":"edsB6X82dI1qKWO8oJq6yZ"},"_color":{"__type__":"cc.Color","r":89,"g":206,"b":73},"_contentSize":{"__type__":"cc.Size","width":300,"height":30},"_anchorPoint":{"__type__":"cc.Vec2"},"_position":{"__type__":"cc.Vec3","x":605,"y":249},"groupIndex":2}],{"__type__":"cc.Material","_name":"builtin-2d-sprite","_effectAsset":{"__uuid__":"28dPjdQWxEQIG3VVl1Qm6T"},"_defines":{"USE_TEXTURE":true},"_props":{}},[{"__type__":"cc.Prefab","_name":"row","data":{"__id__":1}},{"__type__":"cc.Node","_name":"row","_children":[{"__id__":2},{"__id__":3},{"__id__":4}],"_level":1,"_components":[{"__type__":"cc.Sprite","node":{"__id__":1},"_type":2,"_sizeMode":0},{"__type__":"cc.Layout","node":{"__id__":1},"_layoutSize":{"__type__":"cc.Size","width":375,"height":80},"_N$layoutType":1,"_N$paddingLeft":10.2,"_N$paddingRight":10,"_N$spacingX":30},{"__type__":"cc.Widget","node":{"__id__":1},"_alignFlags":40,"_originalWidth":375}],"_prefab":{"__type__":"cc.PrefabInfo","root":{"__id__":1},"asset":{"__uuid__":"fb75PannNN0YjFKlqXw8gS"},"fileId":"a8qoD4o+FMK7+/IwigSKHi"},"_contentSize":{"__type__":"cc.Size","width":375,"height":80},"_position":{"__type__":"cc.Vec3","x":187.5}},{"__type__":"cc.Node","_name":"rank","_parent":{"__id__":1},"_level":4,"_components":[{"__type__":"cc.Label","node":{"__id__":2},"_useOriginalSize":false,"_string":"1","_N$string":"1","_N$horizontalAlign":1,"_N$verticalAlign":1,"_N$overflow":2}],"_prefab":{"__type__":"cc.PrefabInfo","root":{"__id__":1},"asset":{"__uuid__":"fb75PannNN0YjFKlqXw8gS"},"fileId":"f2UqEt+5dBMpa08UuFphRf"},"_contentSize":{"__type__":"cc.Size","width":97.87,"height":40},"_position":{"__type__":"cc.Vec3","x":-128.365}},{"__type__":"cc.Node","_name":"name","_parent":{"__id__":1},"_level":4,"_components":[{"__type__":"cc.Label","node":{"__id__":3},"_useOriginalSize":false,"_string":"shuai","_N$string":"shuai","_N$horizontalAlign":1,"_N$verticalAlign":1,"_N$overflow":2}],"_prefab":{"__type__":"cc.PrefabInfo","root":{"__id__":1},"asset":{"__uuid__":"fb75PannNN0YjFKlqXw8gS"},"fileId":"daO1QBdaNCLI1mOPzQLrTr"},"_contentSize":{"__type__":"cc.Size","width":97.87,"height":40},"_position":{"__type__":"cc.Vec3","x":-0.49500000000000455}},{"__type__":"cc.Node","_name":"score","_parent":{"__id__":1},"_level":4,"_components":[{"__type__":"cc.Label","node":{"__id__":4},"_useOriginalSize":false,"_string":"0","_N$string":"0","_N$horizontalAlign":1,"_N$verticalAlign":1,"_N$overflow":2}],"_prefab":{"__type__":"cc.PrefabInfo","root":{"__id__":1},"asset":{"__uuid__":"fb75PannNN0YjFKlqXw8gS"},"fileId":"11wl2DXj1H+rYMWEbR+/dT"},"_contentSize":{"__type__":"cc.Size","width":97.87,"height":40},"_position":{"__type__":"cc.Vec3","x":127.375}}]]